MANIFEST.in
README.md
scgiwsgi.py
setup.py
scgiwsgi.egg-info/PKG-INFO
scgiwsgi.egg-info/SOURCES.txt
scgiwsgi.egg-info/dependency_links.txt
scgiwsgi.egg-info/requires.txt
scgiwsgi.egg-info/top_level.txt