Metadata-Version: 1.0
Name: scgiwsgi
Version: 0.1
Summary: a WSGI server based on scgi_server
Home-page: https://github.com/dengzhp/scgiwsgi
Author: Deng Zhiping
Author-email: kofreestyler@gmail.com
License: UNKNOWN
Platform: UNKNOWN
